docs/gen_tree.py
param_manager/__init__.py
param_manager/manager.py
site/gen_tree.py
tests/__init__.py
tests/conftest.py
tests/test_apps.py
tests/test_auth.py
tests/test_param_manager.py
tests/test_params.py
param_manager-0.3.7.dist-info/METADATA
param_manager-0.3.7.dist-info/WHEEL
param_manager-0.3.7.dist-info/top_level.txt
param_manager-0.3.7.dist-info/RECORD
