Metadata-Version: 2.1
Name: param-manager
Version: 0.3.7
Summary: Biblioteca para gerenciamento de parâmetros com padrão Singleton,cache e armazenamento local usando TinyDB.
Author-email: MatheusLPolidoro <mattpolidoro4@gmail.com>
Project-URL: Documentation, https://matheuslpolidoro.github.io/param-manager/
Project-URL: Source Code, https://github.com/MatheusLPolidoro/param-manager
Project-URL: Bug Tracker, https://github.com/MatheusLPolidoro/param-manager/issues
Requires-Python: <=3.14,>=3.8
Requires-Dist: tinydb>=4.8.0
Requires-Dist: requests>=2.32.0
Requires-Dist: pycryptodome==3.23.0
Requires-Dist: python-dotenv==1.1.1
